pracscode5/__init__.py
pracscode5/installer.py
pracscode5-0.1.data/scripts/installer.py
pracscode5-0.1.dist-info/METADATA
pracscode5-0.1.dist-info/WHEEL
pracscode5-0.1.dist-info/entry_points.txt
pracscode5-0.1.dist-info/top_level.txt
pracscode5-0.1.dist-info/RECORD
