Metadata-Version: 2.1
Name: pracscode5
Version: 0.1
Summary: Python package to automatically download a file upon installation
Author: Your Name
Requires-Dist: requests
